<?xml version="1.0" encoding="UTF-8"?>
<objects serializationModel="Studio.02.02.00">
	<object class="AudioFile" id="{da9171a6-7f15-4b83-a688-66a0f3878301}">
		<property name="assetPath">
			<value>numbersandlettersandeverythingthatgoeswiththem/NUMBERS AND LETTERS AND EVERYTHING THAT GOES WITH THEM/money with effect/diamonds.wav</value>
		</property>
		<property name="frequencyInKHz">
			<value>44.0999985</value>
		</property>
		<property name="channelCount">
			<value>1</value>
		</property>
		<property name="length">
			<value>0.98600907029478457</value>
		</property>
		<relationship name="masterAssetFolder">
			<destination>{6462cf80-dfb5-4d68-ac39-a82c9eed330d}</destination>
		</relationship>
	</object>
</objects>
